{
    "model_name": "Ensemble",
    "core_models": [
        {
            "model_name": "BootstrapModel",
            "parameters": [
                {
                    "model_name": "Linear",
                    "parameters": {
                        "intercept": 119.36238176682971,
                        "slope": 6.768383411796203,
                        "time_start": 241.13009668058717,
                        "time_length": 12.614782804935373
                    },
                    "bootstrap_num": 0
                },
                {
                    "model_name": "Linear",
                    "parameters": {
                        "intercept": 219.48712161786244,
                        "slope": 2.7337201264859057,
                        "time_start": 237.82586253139533,
                        "time_length": 16.1028577031797
                    },
                    "bootstrap_num": 1
                },
                {
                    "model_name": "Linear",
                    "parameters": {
                        "intercept": 298.0,
                        "slope": -3.0431622250458,
                        "time_start": 278.3855928557906,
                        "time_length": 21.058890533951313
                    },
                    "bootstrap_num": 2
                },
                {
                    "model_name": "Linear",
                    "parameters": {
                        "intercept": 201.44780976636332,
                        "slope": 3.353857417171575,
                        "time_start": 243.1593080983812,
                        "time_length": 10.820507586957817
                    },
                    "bootstrap_num": 3
                },
                {
                    "model_name": "Linear",
                    "parameters": {
                        "intercept": 298.0,
                        "slope": -2.6879888510144516,
                        "time_start": 274.83038750214916,
                        "time_length": 21.21512094124349
                    },
                    "bootstrap_num": 4
                },
                {
                    "model_name": "Linear",
                    "parameters": {
                        "intercept": 99.16223641328475,
                        "slope": 7.8563433057002205,
                        "time_start": 222.14562534416535,
                        "time_length": 31.038826893456562
                    },
                    "bootstrap_num": 5
                },
                {
                    "model_name": "Linear",
                    "parameters": {
                        "intercept": 298.0,
                        "slope": -3.5642154982408014,
                        "time_start": 290.0233707303225,
                        "time_length": 10.867886292714893
                    },
                    "bootstrap_num": 6
                },
                {
                    "model_name": "Linear",
                    "parameters": {
                        "intercept": 298.0,
                        "slope": -2.7432601213071486,
                        "time_start": 286.9079907376824,
                        "time_length": 10.087693331636238
                    },
                    "bootstrap_num": 7
                },
                {
                    "model_name": "Linear",
                    "parameters": {
                        "intercept": 136.32138386205045,
                        "slope": 8.262156529490316,
                        "time_start": 265.18737636220624,
                        "time_length": 10.083175611069883
                    },
                    "bootstrap_num": 8
                },
                {
                    "model_name": "Linear",
                    "parameters": {
                        "intercept": 298.0,
                        "slope": -2.4855873285858476,
                        "time_start": 275.1113601084449,
                        "time_length": 24.574877842969755
                    },
                    "bootstrap_num": 9
                },
                {
                    "model_name": "Linear",
                    "parameters": {
                        "intercept": 282.3087326814695,
                        "slope": -3.730455376052868,
                        "time_start": 274.68995774417624,
                        "time_length": 83.88244178272913
                    },
                    "bootstrap_num": 10
                },
                {
                    "model_name": "Linear",
                    "parameters": {
                        "intercept": 289.5886474884993,
                        "slope": -5.149065167152892,
                        "time_start": 271.2203200789746,
                        "time_length": 86.33943549298762
                    },
                    "bootstrap_num": 11
                },
                {
                    "model_name": "Linear",
                    "parameters": {
                        "intercept": 171.16592282083815,
                        "slope": 5.610094849657864,
                        "time_start": 241.63441066221046,
                        "time_length": 33.233092623541324
                    },
                    "bootstrap_num": 12
                },
                {
                    "model_name": "Linear",
                    "parameters": {
                        "intercept": 297.99999999832744,
                        "slope": -2.4312530568427473,
                        "time_start": 289.0065940448029,
                        "time_length": 10.113312215106873
                    },
                    "bootstrap_num": 13
                },
                {
                    "model_name": "Linear",
                    "parameters": {
                        "intercept": 208.01268751430092,
                        "slope": 3.0386111294571516,
                        "time_start": 217.9773573663592,
                        "time_length": 11.027491006467478
                    },
                    "bootstrap_num": 14
                },
                {
                    "model_name": "Linear",
                    "parameters": {
                        "intercept": 298.0,
                        "slope": -2.6174501731509507,
                        "time_start": 287.2062882007731,
                        "time_length": 12.378413097966757
                    },
                    "bootstrap_num": 15
                },
                {
                    "model_name": "Linear",
                    "parameters": {
                        "intercept": 109.33969569444123,
                        "slope": 10.134059863988199,
                        "time_start": 265.2924933550848,
                        "time_length": 10.404505852865839
                    },
                    "bootstrap_num": 16
                },
                {
                    "model_name": "Linear",
                    "parameters": {
                        "intercept": 143.24867784163717,
                        "slope": 6.102382022819107,
                        "time_start": 216.61034276912642,
                        "time_length": 36.66390859752157
                    },
                    "bootstrap_num": 17
                },
                {
                    "model_name": "Linear",
                    "parameters": {
                        "intercept": 288.4477259889419,
                        "slope": -4.837571198502392,
                        "time_start": 273.02914953638526,
                        "time_length": 84.18323065359002
                    },
                    "bootstrap_num": 18
                },
                {
                    "model_name": "Linear",
                    "parameters": {
                        "intercept": 282.0237396600804,
                        "slope": -3.370366678369455,
                        "time_start": 271.53643956972815,
                        "time_length": 86.97628568736084
                    },
                    "bootstrap_num": 19
                },
                {
                    "model_name": "Linear",
                    "parameters": {
                        "intercept": 298.0,
                        "slope": -3.8267073027871263,
                        "time_start": 295.4606843235233,
                        "time_length": 10.25805732827773
                    },
                    "bootstrap_num": 20
                },
                {
                    "model_name": "Linear",
                    "parameters": {
                        "intercept": 298.0,
                        "slope": -2.3865008619300374,
                        "time_start": 290.22229542380694,
                        "time_length": 10.578625678029873
                    },
                    "bootstrap_num": 21
                },
                {
                    "model_name": "Linear",
                    "parameters": {
                        "intercept": 164.2796053687744,
                        "slope": 6.63128449598751,
                        "time_start": 265.5336664664725,
                        "time_length": 10.058988741990774
                    },
                    "bootstrap_num": 22
                },
                {
                    "model_name": "Linear",
                    "parameters": {
                        "intercept": 210.89007681876714,
                        "slope": 3.9441015966070925,
                        "time_start": 264.37740003325564,
                        "time_length": 10.359287557115607
                    },
                    "bootstrap_num": 23
                },
                {
                    "model_name": "Linear",
                    "parameters": {
                        "intercept": 298.0,
                        "slope": -3.021219190916342,
                        "time_start": 278.08509356791114,
                        "time_length": 21.20755641357317
                    },
                    "bootstrap_num": 24
                },
                {
                    "model_name": "Linear",
                    "parameters": {
                        "intercept": 283.54187077191955,
                        "slope": -4.365580902685706,
                        "time_start": 272.8826573066839,
                        "time_length": 84.11866286824419
                    },
                    "bootstrap_num": 25
                },
                {
                    "model_name": "Linear",
                    "parameters": {
                        "intercept": 298.0,
                        "slope": -3.065305043692035,
                        "time_start": 274.70717484200594,
                        "time_length": 21.741736531576702
                    },
                    "bootstrap_num": 26
                },
                {
                    "model_name": "Linear",
                    "parameters": {
                        "intercept": 298.0,
                        "slope": -2.833233730553246,
                        "time_start": 275.1150447828336,
                        "time_length": 21.412531544806264
                    },
                    "bootstrap_num": 27
                },
                {
                    "model_name": "Linear",
                    "parameters": {
                        "intercept": 126.15349278106767,
                        "slope": 8.864620714621564,
                        "time_start": 265.0915249308612,
                        "time_length": 10.240796450063456
                    },
                    "bootstrap_num": 28
                },
                {
                    "model_name": "Linear",
                    "parameters": {
                        "intercept": 298.0,
                        "slope": -2.828759481680487,
                        "time_start": 274.0842728293958,
                        "time_length": 22.878070879704275
                    },
                    "bootstrap_num": 29
                },
                {
                    "model_name": "Linear",
                    "parameters": {
                        "intercept": 178.4915983612616,
                        "slope": 4.500302341156526,
                        "time_start": 216.71082091233245,
                        "time_length": 37.23438885165777
                    },
                    "bootstrap_num": 30
                },
                {
                    "model_name": "Linear",
                    "parameters": {
                        "intercept": 183.6267635991165,
                        "slope": 4.190472577318088,
                        "time_start": 244.11375556096974,
                        "time_length": 10.818891198328792
                    },
                    "bootstrap_num": 31
                },
                {
                    "model_name": "Linear",
                    "parameters": {
                        "intercept": 145.75409671216113,
                        "slope": 6.068700532133469,
                        "time_start": 222.58570778610272,
                        "time_length": 30.544440737354233
                    },
                    "bootstrap_num": 32
                },
                {
                    "model_name": "Linear",
                    "parameters": {
                        "intercept": 139.76986783885482,
                        "slope": 6.949178963037731,
                        "time_start": 206.44454558624534,
                        "time_length": 65.88102048928447
                    },
                    "bootstrap_num": 33
                },
                {
                    "model_name": "Linear",
                    "parameters": {
                        "intercept": 94.2969273310991,
                        "slope": 10.835371990871046,
                        "time_start": 265.21593479077893,
                        "time_length": 10.626548096406005
                    },
                    "bootstrap_num": 34
                },
                {
                    "model_name": "Linear",
                    "parameters": {
                        "intercept": 133.68386152366733,
                        "slope": 6.475407424582416,
                        "time_start": 241.68312589416206,
                        "time_length": 12.118242141713445
                    },
                    "bootstrap_num": 35
                },
                {
                    "model_name": "Linear",
                    "parameters": {
                        "intercept": 298.0,
                        "slope": -2.9558739626869683,
                        "time_start": 286.67774849904333,
                        "time_length": 10.058207967951205
                    },
                    "bootstrap_num": 36
                },
                {
                    "model_name": "Linear",
                    "parameters": {
                        "intercept": 298.0,
                        "slope": -3.380392509192168,
                        "time_start": 291.177175086026,
                        "time_length": 14.36562195955863
                    },
                    "bootstrap_num": 37
                },
                {
                    "model_name": "Linear",
                    "parameters": {
                        "intercept": 298.0,
                        "slope": -2.3404196006391134,
                        "time_start": 277.9747737181484,
                        "time_length": 21.141106000318295
                    },
                    "bootstrap_num": 38
                },
                {
                    "model_name": "Linear",
                    "parameters": {
                        "intercept": 298.0,
                        "slope": -1.0952174949579243,
                        "time_start": 182.23209804097743,
                        "time_length": 18.728156088632538
                    },
                    "bootstrap_num": 39
                },
                {
                    "model_name": "Linear",
                    "parameters": {
                        "intercept": 298.0,
                        "slope": -2.782647015052976,
                        "time_start": 274.56550408816526,
                        "time_length": 25.02282124229758
                    },
                    "bootstrap_num": 40
                },
                {
                    "model_name": "Linear",
                    "parameters": {
                        "intercept": 282.1477383625774,
                        "slope": -4.100996949435053,
                        "time_start": 274.74606204344406,
                        "time_length": 82.87524399625238
                    },
                    "bootstrap_num": 41
                },
                {
                    "model_name": "Linear",
                    "parameters": {
                        "intercept": 183.9510871319294,
                        "slope": 5.396210467426314,
                        "time_start": 264.4671232366382,
                        "time_length": 10.196233484074867
                    },
                    "bootstrap_num": 42
                },
                {
                    "model_name": "Linear",
                    "parameters": {
                        "intercept": 298.0,
                        "slope": -3.9232260958483485,
                        "time_start": 292.80551091338134,
                        "time_length": 13.687077942498988
                    },
                    "bootstrap_num": 43
                },
                {
                    "model_name": "Linear",
                    "parameters": {
                        "intercept": 180.92442663253,
                        "slope": 4.480738095231407,
                        "time_start": 220.26048762211815,
                        "time_length": 32.24140127538861
                    },
                    "bootstrap_num": 44
                },
                {
                    "model_name": "Linear",
                    "parameters": {
                        "intercept": 294.2656832379292,
                        "slope": -1.891557970754576,
                        "time_start": 287.8279620341393,
                        "time_length": 11.017323991956836
                    },
                    "bootstrap_num": 45
                },
                {
                    "model_name": "Linear",
                    "parameters": {
                        "intercept": 96.21671773505058,
                        "slope": 8.134037392242087,
                        "time_start": 216.9717729609272,
                        "time_length": 36.485456653246125
                    },
                    "bootstrap_num": 46
                },
                {
                    "model_name": "Linear",
                    "parameters": {
                        "intercept": 298.0,
                        "slope": -3.110638448875977,
                        "time_start": 284.28865313318664,
                        "time_length": 11.744923331405644
                    },
                    "bootstrap_num": 47
                },
                {
                    "model_name": "Linear",
                    "parameters": {
                        "intercept": 204.87457973169296,
                        "slope": 3.3288008983108694,
                        "time_start": 244.89828213968508,
                        "time_length": 10.090753470164813
                    },
                    "bootstrap_num": 48
                },
                {
                    "model_name": "Linear",
                    "parameters": {
                        "intercept": 298.0,
                        "slope": -3.8374180352040455,
                        "time_start": 274.9161303760741,
                        "time_length": 21.34414395424436
                    },
                    "bootstrap_num": 49
                }
            ]
        },
        {
            "model_name": "BootstrapModel",
            "parameters": [
                {
                    "model_name": "FallCooling",
                    "parameters": {
                        "t1": 232.30884918032865,
                        "T": 24.623324940118486,
                        "F": 678.0004286804694
                    },
                    "bootstrap_num": 0
                },
                {
                    "model_name": "FallCooling",
                    "parameters": {
                        "t1": 232.72753542049227,
                        "T": 24.871305338975695,
                        "F": 449.31134434296246
                    },
                    "bootstrap_num": 1
                },
                {
                    "model_name": "FallCooling",
                    "parameters": {
                        "t1": 239.5597761316454,
                        "T": 18.401051998877143,
                        "F": 234.38409501918056
                    },
                    "bootstrap_num": 2
                },
                {
                    "model_name": "FallCooling",
                    "parameters": {
                        "t1": 242.88620578296494,
                        "T": 23.57077503588776,
                        "F": 441.53037902681393
                    },
                    "bootstrap_num": 3
                },
                {
                    "model_name": "FallCooling",
                    "parameters": {
                        "t1": 246.13829460839113,
                        "T": 16.112395493607828,
                        "F": 111.92455373081128
                    },
                    "bootstrap_num": 4
                },
                {
                    "model_name": "FallCooling",
                    "parameters": {
                        "t1": 226.8694890163877,
                        "T": 24.666614459133907,
                        "F": 827.0555321859156
                    },
                    "bootstrap_num": 5
                },
                {
                    "model_name": "FallCooling",
                    "parameters": {
                        "t1": 231.01405346955386,
                        "T": 24.859707865458375,
                        "F": 679.1365267546283
                    },
                    "bootstrap_num": 6
                },
                {
                    "model_name": "FallCooling",
                    "parameters": {
                        "t1": 227.73815468548298,
                        "T": 24.861909552271445,
                        "F": 696.1562052299612
                    },
                    "bootstrap_num": 7
                },
                {
                    "model_name": "FallCooling",
                    "parameters": {
                        "t1": 243.21171234654238,
                        "T": 23.603586527540138,
                        "F": 462.37948337604405
                    },
                    "bootstrap_num": 8
                },
                {
                    "model_name": "FallCooling",
                    "parameters": {
                        "t1": 248.05448394516992,
                        "T": 13.88850507776484,
                        "F": 13.783895910671674
                    },
                    "bootstrap_num": 9
                },
                {
                    "model_name": "FallCooling",
                    "parameters": {
                        "t1": 235.05767864513723,
                        "T": 15.753644247579086,
                        "F": 139.57909335916895
                    },
                    "bootstrap_num": 10
                },
                {
                    "model_name": "FallCooling",
                    "parameters": {
                        "t1": 225.1732093476167,
                        "T": 24.880068077558505,
                        "F": 748.2531063529892
                    },
                    "bootstrap_num": 11
                },
                {
                    "model_name": "FallCooling",
                    "parameters": {
                        "t1": 231.34586998863472,
                        "T": 24.587319644644275,
                        "F": 498.8516422855396
                    },
                    "bootstrap_num": 12
                },
                {
                    "model_name": "FallCooling",
                    "parameters": {
                        "t1": 239.89633832470744,
                        "T": 16.183616025368146,
                        "F": 148.26339105880237
                    },
                    "bootstrap_num": 13
                },
                {
                    "model_name": "FallCooling",
                    "parameters": {
                        "t1": 218.08686904378138,
                        "T": 17.623021147882827,
                        "F": 313.61143669001075
                    },
                    "bootstrap_num": 14
                },
                {
                    "model_name": "FallCooling",
                    "parameters": {
                        "t1": 235.91004482431606,
                        "T": 23.245818347288893,
                        "F": 392.73240834036693
                    },
                    "bootstrap_num": 15
                },
                {
                    "model_name": "FallCooling",
                    "parameters": {
                        "t1": 232.21538314579732,
                        "T": 24.609223306042338,
                        "F": 611.3033400117174
                    },
                    "bootstrap_num": 16
                },
                {
                    "model_name": "FallCooling",
                    "parameters": {
                        "t1": 223.28449311411765,
                        "T": 24.4694578834244,
                        "F": 606.2120883771197
                    },
                    "bootstrap_num": 17
                },
                {
                    "model_name": "FallCooling",
                    "parameters": {
                        "t1": 236.5659649526313,
                        "T": 23.611385618430226,
                        "F": 400.8395773393801
                    },
                    "bootstrap_num": 18
                },
                {
                    "model_name": "FallCooling",
                    "parameters": {
                        "t1": 232.87369382066439,
                        "T": 24.902866193631368,
                        "F": 608.9686768385263
                    },
                    "bootstrap_num": 19
                },
                {
                    "model_name": "FallCooling",
                    "parameters": {
                        "t1": 231.96044430238032,
                        "T": 24.862645238024484,
                        "F": 631.7539024902454
                    },
                    "bootstrap_num": 20
                },
                {
                    "model_name": "FallCooling",
                    "parameters": {
                        "t1": 237.90895354731745,
                        "T": 16.218989474964612,
                        "F": 180.40305630808882
                    },
                    "bootstrap_num": 21
                },
                {
                    "model_name": "FallCooling",
                    "parameters": {
                        "t1": 247.87814249998695,
                        "T": 15.806488330814227,
                        "F": 58.12668082880015
                    },
                    "bootstrap_num": 22
                },
                {
                    "model_name": "FallCooling",
                    "parameters": {
                        "t1": 226.1212136648398,
                        "T": 24.909748956980255,
                        "F": 897.1990156674075
                    },
                    "bootstrap_num": 23
                },
                {
                    "model_name": "FallCooling",
                    "parameters": {
                        "t1": 236.056112647219,
                        "T": 18.58124785974269,
                        "F": 271.5630848042702
                    },
                    "bootstrap_num": 24
                },
                {
                    "model_name": "FallCooling",
                    "parameters": {
                        "t1": 265.9267824892378,
                        "T": 16.037978344187014,
                        "F": 53.81656583713021
                    },
                    "bootstrap_num": 25
                },
                {
                    "model_name": "FallCooling",
                    "parameters": {
                        "t1": 232.17459112998992,
                        "T": 24.664072417254125,
                        "F": 630.1614692441042
                    },
                    "bootstrap_num": 26
                },
                {
                    "model_name": "FallCooling",
                    "parameters": {
                        "t1": 235.86403591331006,
                        "T": 23.631353583172505,
                        "F": 596.8353147012995
                    },
                    "bootstrap_num": 27
                },
                {
                    "model_name": "FallCooling",
                    "parameters": {
                        "t1": 224.63352858707412,
                        "T": 23.227769002826093,
                        "F": 509.83538442122267
                    },
                    "bootstrap_num": 28
                },
                {
                    "model_name": "FallCooling",
                    "parameters": {
                        "t1": 235.45435012300075,
                        "T": 24.6845041767374,
                        "F": 517.7105618346258
                    },
                    "bootstrap_num": 29
                },
                {
                    "model_name": "FallCooling",
                    "parameters": {
                        "t1": 225.2803757260212,
                        "T": 24.872325029311686,
                        "F": 750.5414399804005
                    },
                    "bootstrap_num": 30
                },
                {
                    "model_name": "FallCooling",
                    "parameters": {
                        "t1": 237.4448897019875,
                        "T": 16.256281775496063,
                        "F": 149.0855597444558
                    },
                    "bootstrap_num": 31
                },
                {
                    "model_name": "FallCooling",
                    "parameters": {
                        "t1": 232.45464888357043,
                        "T": 24.89052167607335,
                        "F": 608.5531190508991
                    },
                    "bootstrap_num": 32
                },
                {
                    "model_name": "FallCooling",
                    "parameters": {
                        "t1": 236.20259246318966,
                        "T": 23.482092509994196,
                        "F": 467.51930343293174
                    },
                    "bootstrap_num": 33
                },
                {
                    "model_name": "FallCooling",
                    "parameters": {
                        "t1": 232.86408818706366,
                        "T": 24.565179441176898,
                        "F": 563.765037099321
                    },
                    "bootstrap_num": 34
                },
                {
                    "model_name": "FallCooling",
                    "parameters": {
                        "t1": 236.86823887457712,
                        "T": 23.509213687630464,
                        "F": 467.9719956033699
                    },
                    "bootstrap_num": 35
                },
                {
                    "model_name": "FallCooling",
                    "parameters": {
                        "t1": 224.49144985061392,
                        "T": 23.210139290881248,
                        "F": 639.6920824379785
                    },
                    "bootstrap_num": 36
                },
                {
                    "model_name": "FallCooling",
                    "parameters": {
                        "t1": 268.8989371604856,
                        "T": 17.296917968548264,
                        "F": 78.96919727981145
                    },
                    "bootstrap_num": 37
                },
                {
                    "model_name": "FallCooling",
                    "parameters": {
                        "t1": 231.0531198729479,
                        "T": 24.87302320414248,
                        "F": 616.8783176411156
                    },
                    "bootstrap_num": 38
                },
                {
                    "model_name": "FallCooling",
                    "parameters": {
                        "t1": 235.71100089432971,
                        "T": 23.627097670314974,
                        "F": 484.1879642108503
                    },
                    "bootstrap_num": 39
                },
                {
                    "model_name": "FallCooling",
                    "parameters": {
                        "t1": 236.00339115592215,
                        "T": 24.674522389389274,
                        "F": 609.2813267557696
                    },
                    "bootstrap_num": 40
                },
                {
                    "model_name": "FallCooling",
                    "parameters": {
                        "t1": 205.82849068928635,
                        "T": 23.30880148552344,
                        "F": 910.9175517724584
                    },
                    "bootstrap_num": 41
                },
                {
                    "model_name": "FallCooling",
                    "parameters": {
                        "t1": 224.2811668571444,
                        "T": 24.484256247875102,
                        "F": 747.747699816904
                    },
                    "bootstrap_num": 42
                },
                {
                    "model_name": "FallCooling",
                    "parameters": {
                        "t1": 236.03060740979413,
                        "T": 23.341721528112263,
                        "F": 463.17865545055196
                    },
                    "bootstrap_num": 43
                },
                {
                    "model_name": "FallCooling",
                    "parameters": {
                        "t1": 235.1250131089056,
                        "T": 23.472500849443662,
                        "F": 390.8048924841485
                    },
                    "bootstrap_num": 44
                },
                {
                    "model_name": "FallCooling",
                    "parameters": {
                        "t1": 259.5973465354309,
                        "T": 12.142885753640382,
                        "F": 12.108634559044901
                    },
                    "bootstrap_num": 45
                },
                {
                    "model_name": "FallCooling",
                    "parameters": {
                        "t1": 231.75248085739958,
                        "T": 24.85507272721268,
                        "F": 618.060362944055
                    },
                    "bootstrap_num": 46
                },
                {
                    "model_name": "FallCooling",
                    "parameters": {
                        "t1": 223.84262976618427,
                        "T": 20.933694195290386,
                        "F": 487.72999944093664
                    },
                    "bootstrap_num": 47
                },
                {
                    "model_name": "FallCooling",
                    "parameters": {
                        "t1": 232.30064584663234,
                        "T": 24.578840552762788,
                        "F": 679.7277796505333
                    },
                    "bootstrap_num": 48
                },
                {
                    "model_name": "FallCooling",
                    "parameters": {
                        "t1": 260.13261405785966,
                        "T": 11.786990012892618,
                        "F": 9.351877126312331
                    },
                    "bootstrap_num": 49
                }
            ]
        }
    ]
}