{
    "model_name": "BootstrapModel",
    "parameters": [
        {
            "model_name": "Naive",
            "parameters": {
                "intercept": -67.0,
                "slope": 4.409576868768626
            },
            "bootstrap_num": 0
        },
        {
            "model_name": "Naive",
            "parameters": {
                "intercept": -67.0,
                "slope": 4.406770770744265
            },
            "bootstrap_num": 1
        },
        {
            "model_name": "Naive",
            "parameters": {
                "intercept": -67.0,
                "slope": 4.4154187789602135
            },
            "bootstrap_num": 2
        },
        {
            "model_name": "Naive",
            "parameters": {
                "intercept": -67.0,
                "slope": 4.490669440820675
            },
            "bootstrap_num": 3
        },
        {
            "model_name": "Naive",
            "parameters": {
                "intercept": -67.0,
                "slope": 4.440633697912468
            },
            "bootstrap_num": 4
        },
        {
            "model_name": "Naive",
            "parameters": {
                "intercept": -67.0,
                "slope": 4.396434863206777
            },
            "bootstrap_num": 5
        },
        {
            "model_name": "Naive",
            "parameters": {
                "intercept": -67.0,
                "slope": 4.3790906583149045
            },
            "bootstrap_num": 6
        },
        {
            "model_name": "Naive",
            "parameters": {
                "intercept": -67.0,
                "slope": 4.472348252863749
            },
            "bootstrap_num": 7
        },
        {
            "model_name": "Naive",
            "parameters": {
                "intercept": -67.0,
                "slope": 4.443349276966557
            },
            "bootstrap_num": 8
        },
        {
            "model_name": "Naive",
            "parameters": {
                "intercept": -67.0,
                "slope": 4.4780593295911935
            },
            "bootstrap_num": 9
        },
        {
            "model_name": "Naive",
            "parameters": {
                "intercept": -67.0,
                "slope": 4.4683691388658895
            },
            "bootstrap_num": 10
        },
        {
            "model_name": "Naive",
            "parameters": {
                "intercept": -67.0,
                "slope": 4.448163266009121
            },
            "bootstrap_num": 11
        },
        {
            "model_name": "Naive",
            "parameters": {
                "intercept": -67.0,
                "slope": 4.476686259817852
            },
            "bootstrap_num": 12
        },
        {
            "model_name": "Naive",
            "parameters": {
                "intercept": -67.0,
                "slope": 4.469012129123999
            },
            "bootstrap_num": 13
        },
        {
            "model_name": "Naive",
            "parameters": {
                "intercept": -67.0,
                "slope": 4.471673992852245
            },
            "bootstrap_num": 14
        },
        {
            "model_name": "Naive",
            "parameters": {
                "intercept": -67.0,
                "slope": 4.48313671571548
            },
            "bootstrap_num": 15
        },
        {
            "model_name": "Naive",
            "parameters": {
                "intercept": -67.0,
                "slope": 4.403607199685243
            },
            "bootstrap_num": 16
        },
        {
            "model_name": "Naive",
            "parameters": {
                "intercept": -67.0,
                "slope": 4.40984105763345
            },
            "bootstrap_num": 17
        },
        {
            "model_name": "Naive",
            "parameters": {
                "intercept": -67.0,
                "slope": 4.446546263365882
            },
            "bootstrap_num": 18
        },
        {
            "model_name": "Naive",
            "parameters": {
                "intercept": -67.0,
                "slope": 4.41727436442994
            },
            "bootstrap_num": 19
        },
        {
            "model_name": "Naive",
            "parameters": {
                "intercept": -67.0,
                "slope": 4.435712105105719
            },
            "bootstrap_num": 20
        },
        {
            "model_name": "Naive",
            "parameters": {
                "intercept": -67.0,
                "slope": 4.416949233855828
            },
            "bootstrap_num": 21
        },
        {
            "model_name": "Naive",
            "parameters": {
                "intercept": -67.0,
                "slope": 4.392335993395644
            },
            "bootstrap_num": 22
        },
        {
            "model_name": "Naive",
            "parameters": {
                "intercept": -67.0,
                "slope": 4.49601854414543
            },
            "bootstrap_num": 23
        },
        {
            "model_name": "Naive",
            "parameters": {
                "intercept": -67.0,
                "slope": 4.427990656895525
            },
            "bootstrap_num": 24
        },
        {
            "model_name": "Naive",
            "parameters": {
                "intercept": -67.0,
                "slope": 4.481699078799954
            },
            "bootstrap_num": 25
        },
        {
            "model_name": "Naive",
            "parameters": {
                "intercept": -67.0,
                "slope": 4.421044411768796
            },
            "bootstrap_num": 26
        },
        {
            "model_name": "Naive",
            "parameters": {
                "intercept": -67.0,
                "slope": 4.397721539291318
            },
            "bootstrap_num": 27
        },
        {
            "model_name": "Naive",
            "parameters": {
                "intercept": -67.0,
                "slope": 4.462813383061516
            },
            "bootstrap_num": 28
        },
        {
            "model_name": "Naive",
            "parameters": {
                "intercept": -67.0,
                "slope": 4.394379891923003
            },
            "bootstrap_num": 29
        },
        {
            "model_name": "Naive",
            "parameters": {
                "intercept": -67.0,
                "slope": 4.382115217762954
            },
            "bootstrap_num": 30
        },
        {
            "model_name": "Naive",
            "parameters": {
                "intercept": -67.0,
                "slope": 4.468599239907428
            },
            "bootstrap_num": 31
        },
        {
            "model_name": "Naive",
            "parameters": {
                "intercept": -67.0,
                "slope": 4.433052333118381
            },
            "bootstrap_num": 32
        },
        {
            "model_name": "Naive",
            "parameters": {
                "intercept": -67.0,
                "slope": 4.407112813331069
            },
            "bootstrap_num": 33
        },
        {
            "model_name": "Naive",
            "parameters": {
                "intercept": -67.0,
                "slope": 4.386593685359836
            },
            "bootstrap_num": 34
        },
        {
            "model_name": "Naive",
            "parameters": {
                "intercept": -67.0,
                "slope": 4.431855656054042
            },
            "bootstrap_num": 35
        },
        {
            "model_name": "Naive",
            "parameters": {
                "intercept": -67.0,
                "slope": 4.452336980966764
            },
            "bootstrap_num": 36
        },
        {
            "model_name": "Naive",
            "parameters": {
                "intercept": -67.0,
                "slope": 4.441684221810333
            },
            "bootstrap_num": 37
        },
        {
            "model_name": "Naive",
            "parameters": {
                "intercept": -67.0,
                "slope": 4.506935073193734
            },
            "bootstrap_num": 38
        },
        {
            "model_name": "Naive",
            "parameters": {
                "intercept": -67.0,
                "slope": 4.409359479622079
            },
            "bootstrap_num": 39
        },
        {
            "model_name": "Naive",
            "parameters": {
                "intercept": -67.0,
                "slope": 4.491643548955692
            },
            "bootstrap_num": 40
        },
        {
            "model_name": "Naive",
            "parameters": {
                "intercept": -67.0,
                "slope": 4.429935888363317
            },
            "bootstrap_num": 41
        },
        {
            "model_name": "Naive",
            "parameters": {
                "intercept": -67.0,
                "slope": 4.412981501074093
            },
            "bootstrap_num": 42
        },
        {
            "model_name": "Naive",
            "parameters": {
                "intercept": -67.0,
                "slope": 4.357933975458973
            },
            "bootstrap_num": 43
        },
        {
            "model_name": "Naive",
            "parameters": {
                "intercept": -67.0,
                "slope": 4.416805476820357
            },
            "bootstrap_num": 44
        },
        {
            "model_name": "Naive",
            "parameters": {
                "intercept": -67.0,
                "slope": 4.451348269643062
            },
            "bootstrap_num": 45
        },
        {
            "model_name": "Naive",
            "parameters": {
                "intercept": -67.0,
                "slope": 4.504269205574741
            },
            "bootstrap_num": 46
        },
        {
            "model_name": "Naive",
            "parameters": {
                "intercept": -67.0,
                "slope": 4.395371572961848
            },
            "bootstrap_num": 47
        },
        {
            "model_name": "Naive",
            "parameters": {
                "intercept": -67.0,
                "slope": 4.413772467440859
            },
            "bootstrap_num": 48
        },
        {
            "model_name": "Naive",
            "parameters": {
                "intercept": -67.0,
                "slope": 4.510354560062244
            },
            "bootstrap_num": 49
        }
    ]
}